mcp_proxy/__init__.py
mcp_proxy/__main__.py
mcp_proxy/config_loader.py
mcp_proxy/mcp_server.py
mcp_proxy/proxy_server.py
mcp_proxy/py.typed
mcp_proxy/sse_client.py
mcp_proxy/streamablehttp_client.py
mcp_proxy-0.9.0.dist-info/licenses/LICENSE
mcp_proxy-0.9.0.dist-info/METADATA
mcp_proxy-0.9.0.dist-info/WHEEL
mcp_proxy-0.9.0.dist-info/entry_points.txt
mcp_proxy-0.9.0.dist-info/top_level.txt
mcp_proxy-0.9.0.dist-info/RECORD
