Metadata-Version: 2.4
Name: mcp-proxy
Version: 0.9.0
Summary: A MCP server which proxies requests to a remote MCP server over SSE transport.
Author-email: Sergey Parfenyuk <sergey.parfenyuk@gmail.com>
License: MIT License
Project-URL: Homepage, https://github.com/sparfenyuk/mcp-proxy
Project-URL: Source, https://github.com/sparfenyuk/mcp-proxy
Project-URL: Documentation, https://github.com/sparfenyuk/mcp-proxy
Project-URL: Changelog, https://github.com/sparfenyuk/mcp-proxy/releases
Classifier: Development Status :: 4 - Beta
Classifier: Environment :: Console
Classifier: Intended Audience :: Developers
Classifier: Intended Audience :: Information Technology
Classifier: Intended Audience :: System Administrators
Classifier: License :: OSI Approved :: MIT License
Classifier: Operating System :: MacOS
Classifier: Operating System :: POSIX :: Linux
Classifier: Operating System :: Unix
Classifier: Programming Language :: Python
Classifier: Programming Language :: Python :: 3
Classifier: Programming Language :: Python :: 3 :: Only
Classifier: Programming Language :: Python :: 3.10
Classifier: Programming Language :: Python :: 3.11
Classifier: Programming Language :: Python :: 3.12
Classifier: Programming Language :: Python :: 3.13
Classifier: Topic :: Software Development :: Libraries :: Python Modules
Classifier: Topic :: Utilities
Classifier: Typing :: Typed
Requires-Python: >=3.10
License-File: LICENSE
Requires-Dist: mcp==1.9.4
Requires-Dist: uvicorn>=0.34.0
Dynamic: license-file
